<?xml version="1.0" encoding="UTF-8"?>
<persons>
    <person>
        <tax_number>778899112</tax_number>
        <full_name>Ügyvezető Mihály</full_name>
        <id>1</id>
        <id2>1</id2>
        <login_date>2015.09.08</login_date>
        <logout_date>2021.09.08</logout_date>
        <email>ugyvezeto.mihaly@gmail.com</email>
    </person>
    <person>
        <tax_number>9999999</tax_number>
        <full_name>Ügyvezető Mihály2</full_name>
        <id>2</id>
        <id2>2</id2>
        <login_date>2016.09.08</login_date>
        <logout_date>2021.09.08</logout_date>
        <email>ugyvezeto.mihaly2@gmail.com</email>
    </person>
    <person>
        <tax_number>1111111</tax_number>
        <full_name>Ügyvezető Mihály3</full_name>
        <id>3</id>
        <id2>3</id2>
        <login_date>2016.02.02</login_date>
        <logout_date>2020.02.11</logout_date>
        <email>ugyvezeto.mihaly103@gmail.com</email>
    </person>
        <person>
        <tax_number>435435435</tax_number>
        <full_name>Ügyvezető Mihály4</full_name>
        <id>4</id>
        <id2>5</id2>
        <login_date>2017.04.30</login_date>
        <logout_date>2021.02.11</logout_date>
        <email>ugyvezeto@gmail.com</email>
    </person>
    <person>
        <tax_number>8483241</tax_number>
        <full_name>Ügyvezető Mihály5</full_name>
        <id>6</id>
        <id2>7</id2>
        <login_date>2016.11.12</login_date>
        <logout_date>2021.02.11</logout_date>
        <email>ugyvezeto.mihaly7@gmail.com</email>
    </person>
</persons>